custom_library_22/__init__.py
custom_library_22/custom_library_22.py
tests/__init__.py
tests/test_custom_library.py
custom_library_22-1.1.1.dist-info/LICENSE
custom_library_22-1.1.1.dist-info/METADATA
custom_library_22-1.1.1.dist-info/WHEEL
custom_library_22-1.1.1.dist-info/top_level.txt
custom_library_22-1.1.1.dist-info/RECORD
