Metadata-Version: 2.1
Name: custom-library_22
Version: 1.1.1
Summary: A utility library for S3 file management and helper functions
Home-page: https://github.com/yourusername/custom-library
Author: Your Name
Author-email: your.email@example.com
Classifier: Programming Language :: Python :: 3
Classifier: License :: OSI Approved :: MIT License
Classifier: Operating System :: OS Independent
Requires-Python: >=3.6
License-File: LICENSE
Requires-Dist: boto3
Requires-Dist: werkzeug
